{"nodes": [{"id": "c_stayflexi_src_common_contracts_ihotelservice_ts", "label": "IHotelService.ts", "file_type": "code", "source_file": "C:\\Stayflexi\\src\\common\\contracts\\IHotelService.ts", "source_location": "L1"}, {"id": "contracts_ihotelservice_hotelsummary", "label": "HotelSummary", "file_type": "code", "source_file": "C:\\Stayflexi\\src\\common\\contracts\\IHotelService.ts", "source_location": "L3"}, {"id": "contracts_ihotelservice_ihotelservice", "label": "IHotelService", "file_type": "code", "source_file": "C:\\Stayflexi\\src\\common\\contracts\\IHotelService.ts", "source_location": "L15"}], "edges": [{"source": "c_stayflexi_src_common_contracts_ihotelservice_ts", "target": "c_stayflexi_src_common_types_index_ts", "relation": "imports_from", "context": "import", "confidence": "EXTRACTED", "source_file": "C:\\Stayflexi\\src\\common\\contracts\\IHotelService.ts", "source_location": "L1", "weight": 1.0}, {"source": "c_stayflexi_src_common_contracts_ihotelservice_ts", "target": "types_index_nullable", "relation": "imports", "context": "import", "confidence": "EXTRACTED", "source_file": "C:\\Stayflexi\\src\\common\\contracts\\IHotelService.ts", "source_location": "L1", "weight": 1.0}, {"source": "c_stayflexi_src_common_contracts_ihotelservice_ts", "target": "types_index_paginatedresult", "relation": "imports", "context": "import", "confidence": "EXTRACTED", "source_file": "C:\\Stayflexi\\src\\common\\contracts\\IHotelService.ts", "source_location": "L1", "weight": 1.0}, {"source": "c_stayflexi_src_common_contracts_ihotelservice_ts", "target": "types_index_paginationparams", "relation": "imports", "context": "import", "confidence": "EXTRACTED", "source_file": "C:\\Stayflexi\\src\\common\\contracts\\IHotelService.ts", "source_location": "L1", "weight": 1.0}, {"source": "c_stayflexi_src_common_contracts_ihotelservice_ts", "target": "contracts_ihotelservice_hotelsummary", "relation": "contains", "confidence": "EXTRACTED", "source_file": "C:\\Stayflexi\\src\\common\\contracts\\IHotelService.ts", "source_location": "L3", "weight": 1.0}, {"source": "c_stayflexi_src_common_contracts_ihotelservice_ts", "target": "contracts_ihotelservice_ihotelservice", "relation": "contains", "confidence": "EXTRACTED", "source_file": "C:\\Stayflexi\\src\\common\\contracts\\IHotelService.ts", "source_location": "L15", "weight": 1.0}], "raw_calls": []}