{"nodes": [{"id": "c_stayflexi_services_notification_service_src_domain_entities_notification_ts", "label": "Notification.ts", "file_type": "code", "source_file": "C:\\Stayflexi\\services\\notification-service\\src\\domain\\entities\\Notification.ts", "source_location": "L1"}, {"id": "entities_notification_notificationprops", "label": "NotificationProps", "file_type": "code", "source_file": "C:\\Stayflexi\\services\\notification-service\\src\\domain\\entities\\Notification.ts", "source_location": "L1"}, {"id": "entities_notification_notification", "label": "Notification", "file_type": "code", "source_file": "C:\\Stayflexi\\services\\notification-service\\src\\domain\\entities\\Notification.ts", "source_location": "L20"}, {"id": "entities_notification_notification_constructor", "label": ".constructor()", "file_type": "code", "source_file": "C:\\Stayflexi\\services\\notification-service\\src\\domain\\entities\\Notification.ts", "source_location": "L21"}, {"id": "entities_notification_notification_id", "label": ".id()", "file_type": "code", "source_file": "C:\\Stayflexi\\services\\notification-service\\src\\domain\\entities\\Notification.ts", "source_location": "L23"}, {"id": "entities_notification_notification_organizationid", "label": ".organizationId()", "file_type": "code", "source_file": "C:\\Stayflexi\\services\\notification-service\\src\\domain\\entities\\Notification.ts", "source_location": "L24"}, {"id": "entities_notification_notification_hotelid", "label": ".hotelId()", "file_type": "code", "source_file": "C:\\Stayflexi\\services\\notification-service\\src\\domain\\entities\\Notification.ts", "source_location": "L25"}, {"id": "entities_notification_notification_notificationtype", "label": ".notificationType()", "file_type": "code", "source_file": "C:\\Stayflexi\\services\\notification-service\\src\\domain\\entities\\Notification.ts", "source_location": "L26"}, {"id": "entities_notification_notification_recipient", "label": ".recipient()", "file_type": "code", "source_file": "C:\\Stayflexi\\services\\notification-service\\src\\domain\\entities\\Notification.ts", "source_location": "L27"}, {"id": "entities_notification_notification_subject", "label": ".subject()", "file_type": "code", "source_file": "C:\\Stayflexi\\services\\notification-service\\src\\domain\\entities\\Notification.ts", "source_location": "L28"}, {"id": "entities_notification_notification_message", "label": ".message()", "file_type": "code", "source_file": "C:\\Stayflexi\\services\\notification-service\\src\\domain\\entities\\Notification.ts", "source_location": "L29"}, {"id": "entities_notification_notification_deliverystatus", "label": ".deliveryStatus()", "file_type": "code", "source_file": "C:\\Stayflexi\\services\\notification-service\\src\\domain\\entities\\Notification.ts", "source_location": "L30"}, {"id": "entities_notification_notification_retrycount", "label": ".retryCount()", "file_type": "code", "source_file": "C:\\Stayflexi\\services\\notification-service\\src\\domain\\entities\\Notification.ts", "source_location": "L31"}, {"id": "entities_notification_notification_maxretries", "label": ".maxRetries()", "file_type": "code", "source_file": "C:\\Stayflexi\\services\\notification-service\\src\\domain\\entities\\Notification.ts", "source_location": "L32"}, {"id": "entities_notification_notification_scheduledat", "label": ".scheduledAt()", "file_type": "code", "source_file": "C:\\Stayflexi\\services\\notification-service\\src\\domain\\entities\\Notification.ts", "source_location": "L33"}, {"id": "entities_notification_notification_deliveredat", "label": ".deliveredAt()", "file_type": "code", "source_file": "C:\\Stayflexi\\services\\notification-service\\src\\domain\\entities\\Notification.ts", "source_location": "L34"}, {"id": "entities_notification_notification_failedreason", "label": ".failedReason()", "file_type": "code", "source_file": "C:\\Stayflexi\\services\\notification-service\\src\\domain\\entities\\Notification.ts", "source_location": "L35"}, {"id": "entities_notification_notification_metadata", "label": ".metadata()", "file_type": "code", "source_file": "C:\\Stayflexi\\services\\notification-service\\src\\domain\\entities\\Notification.ts", "source_location": "L36"}, {"id": "entities_notification_notification_createdat", "label": ".createdAt()", "file_type": "code", "source_file": "C:\\Stayflexi\\services\\notification-service\\src\\domain\\entities\\Notification.ts", "source_location": "L37"}, {"id": "entities_notification_notification_canretry", "label": ".canRetry()", "file_type": "code", "source_file": "C:\\Stayflexi\\services\\notification-service\\src\\domain\\entities\\Notification.ts", "source_location": "L39"}, {"id": "entities_notification_notification_ispending", "label": ".isPending()", "file_type": "code", "source_file": "C:\\Stayflexi\\services\\notification-service\\src\\domain\\entities\\Notification.ts", "source_location": "L43"}, {"id": "entities_notification_notification_isdelivered", "label": ".isDelivered()", "file_type": "code", "source_file": "C:\\Stayflexi\\services\\notification-service\\src\\domain\\entities\\Notification.ts", "source_location": "L47"}, {"id": "entities_notification_notification_belongstoorganization", "label": ".belongsToOrganization()", "file_type": "code", "source_file": "C:\\Stayflexi\\services\\notification-service\\src\\domain\\entities\\Notification.ts", "source_location": "L51"}, {"id": "entities_notification_notification_tojson", "label": ".toJSON()", "file_type": "code", "source_file": "C:\\Stayflexi\\services\\notification-service\\src\\domain\\entities\\Notification.ts", "source_location": "L55"}], "edges": [{"source": "c_stayflexi_services_notification_service_src_domain_entities_notification_ts", "target": "entities_notification_notificationprops", "relation": "contains", "confidence": "EXTRACTED", "source_file": "C:\\Stayflexi\\services\\notification-service\\src\\domain\\entities\\Notification.ts", "source_location": "L1", "weight": 1.0}, {"source": "c_stayflexi_services_notification_service_src_domain_entities_notification_ts", "target": "entities_notification_notification", "relation": "contains", "confidence": "EXTRACTED", "source_file": "C:\\Stayflexi\\services\\notification-service\\src\\domain\\entities\\Notification.ts", "source_location": "L20", "weight": 1.0}, {"source": "entities_notification_notification", "target": "entities_notification_notification_constructor", "relation": "method", "confidence": "EXTRACTED", "source_file": "C:\\Stayflexi\\services\\notification-service\\src\\domain\\entities\\Notification.ts", "source_location": "L21", "weight": 1.0}, {"source": "entities_notification_notification", "target": "entities_notification_notification_id", "relation": "method", "confidence": "EXTRACTED", "source_file": "C:\\Stayflexi\\services\\notification-service\\src\\domain\\entities\\Notification.ts", "source_location": "L23", "weight": 1.0}, {"source": "entities_notification_notification", "target": "entities_notification_notification_organizationid", "relation": "method", "confidence": "EXTRACTED", "source_file": "C:\\Stayflexi\\services\\notification-service\\src\\domain\\entities\\Notification.ts", "source_location": "L24", "weight": 1.0}, {"source": "entities_notification_notification", "target": "entities_notification_notification_hotelid", "relation": "method", "confidence": "EXTRACTED", "source_file": "C:\\Stayflexi\\services\\notification-service\\src\\domain\\entities\\Notification.ts", "source_location": "L25", "weight": 1.0}, {"source": "entities_notification_notification", "target": "entities_notification_notification_notificationtype", "relation": "method", "confidence": "EXTRACTED", "source_file": "C:\\Stayflexi\\services\\notification-service\\src\\domain\\entities\\Notification.ts", "source_location": "L26", "weight": 1.0}, {"source": "entities_notification_notification", "target": "entities_notification_notification_recipient", "relation": "method", "confidence": "EXTRACTED", "source_file": "C:\\Stayflexi\\services\\notification-service\\src\\domain\\entities\\Notification.ts", "source_location": "L27", "weight": 1.0}, {"source": "entities_notification_notification", "target": "entities_notification_notification_subject", "relation": "method", "confidence": "EXTRACTED", "source_file": "C:\\Stayflexi\\services\\notification-service\\src\\domain\\entities\\Notification.ts", "source_location": "L28", "weight": 1.0}, {"source": "entities_notification_notification", "target": "entities_notification_notification_message", "relation": "method", "confidence": "EXTRACTED", "source_file": "C:\\Stayflexi\\services\\notification-service\\src\\domain\\entities\\Notification.ts", "source_location": "L29", "weight": 1.0}, {"source": "entities_notification_notification", "target": "entities_notification_notification_deliverystatus", "relation": "method", "confidence": "EXTRACTED", "source_file": "C:\\Stayflexi\\services\\notification-service\\src\\domain\\entities\\Notification.ts", "source_location": "L30", "weight": 1.0}, {"source": "entities_notification_notification", "target": "entities_notification_notification_retrycount", "relation": "method", "confidence": "EXTRACTED", "source_file": "C:\\Stayflexi\\services\\notification-service\\src\\domain\\entities\\Notification.ts", "source_location": "L31", "weight": 1.0}, {"source": "entities_notification_notification", "target": "entities_notification_notification_maxretries", "relation": "method", "confidence": "EXTRACTED", "source_file": "C:\\Stayflexi\\services\\notification-service\\src\\domain\\entities\\Notification.ts", "source_location": "L32", "weight": 1.0}, {"source": "entities_notification_notification", "target": "entities_notification_notification_scheduledat", "relation": "method", "confidence": "EXTRACTED", "source_file": "C:\\Stayflexi\\services\\notification-service\\src\\domain\\entities\\Notification.ts", "source_location": "L33", "weight": 1.0}, {"source": "entities_notification_notification", "target": "entities_notification_notification_deliveredat", "relation": "method", "confidence": "EXTRACTED", "source_file": "C:\\Stayflexi\\services\\notification-service\\src\\domain\\entities\\Notification.ts", "source_location": "L34", "weight": 1.0}, {"source": "entities_notification_notification", "target": "entities_notification_notification_failedreason", "relation": "method", "confidence": "EXTRACTED", "source_file": "C:\\Stayflexi\\services\\notification-service\\src\\domain\\entities\\Notification.ts", "source_location": "L35", "weight": 1.0}, {"source": "entities_notification_notification", "target": "entities_notification_notification_metadata", "relation": "method", "confidence": "EXTRACTED", "source_file": "C:\\Stayflexi\\services\\notification-service\\src\\domain\\entities\\Notification.ts", "source_location": "L36", "weight": 1.0}, {"source": "entities_notification_notification", "target": "entities_notification_notification_createdat", "relation": "method", "confidence": "EXTRACTED", "source_file": "C:\\Stayflexi\\services\\notification-service\\src\\domain\\entities\\Notification.ts", "source_location": "L37", "weight": 1.0}, {"source": "entities_notification_notification", "target": "entities_notification_notification_canretry", "relation": "method", "confidence": "EXTRACTED", "source_file": "C:\\Stayflexi\\services\\notification-service\\src\\domain\\entities\\Notification.ts", "source_location": "L39", "weight": 1.0}, {"source": "entities_notification_notification", "target": "entities_notification_notification_ispending", "relation": "method", "confidence": "EXTRACTED", "source_file": "C:\\Stayflexi\\services\\notification-service\\src\\domain\\entities\\Notification.ts", "source_location": "L43", "weight": 1.0}, {"source": "entities_notification_notification", "target": "entities_notification_notification_isdelivered", "relation": "method", "confidence": "EXTRACTED", "source_file": "C:\\Stayflexi\\services\\notification-service\\src\\domain\\entities\\Notification.ts", "source_location": "L47", "weight": 1.0}, {"source": "entities_notification_notification", "target": "entities_notification_notification_belongstoorganization", "relation": "method", "confidence": "EXTRACTED", "source_file": "C:\\Stayflexi\\services\\notification-service\\src\\domain\\entities\\Notification.ts", "source_location": "L51", "weight": 1.0}, {"source": "entities_notification_notification", "target": "entities_notification_notification_tojson", "relation": "method", "confidence": "EXTRACTED", "source_file": "C:\\Stayflexi\\services\\notification-service\\src\\domain\\entities\\Notification.ts", "source_location": "L55", "weight": 1.0}], "raw_calls": []}