{"nodes": [{"id": "c_stayflexi_src_modules_invoice_services_billingservice_ts", "label": "BillingService.ts", "file_type": "code", "source_file": "C:\\Stayflexi\\src\\modules\\invoice\\services\\BillingService.ts", "source_location": "L1"}, {"id": "services_billingservice_billingsummary", "label": "BillingSummary", "file_type": "code", "source_file": "C:\\Stayflexi\\src\\modules\\invoice\\services\\BillingService.ts", "source_location": "L8"}, {"id": "services_billingservice_billingservice", "label": "BillingService", "file_type": "code", "source_file": "C:\\Stayflexi\\src\\modules\\invoice\\services\\BillingService.ts", "source_location": "L30"}, {"id": "services_billingservice_billingservice_constructor", "label": ".constructor()", "file_type": "code", "source_file": "C:\\Stayflexi\\src\\modules\\invoice\\services\\BillingService.ts", "source_location": "L33"}, {"id": "services_billingservice_billingservice_getbillingsummary", "label": ".getBillingSummary()", "file_type": "code", "source_file": "C:\\Stayflexi\\src\\modules\\invoice\\services\\BillingService.ts", "source_location": "L39"}], "edges": [{"source": "c_stayflexi_src_modules_invoice_services_billingservice_ts", "target": "c_stayflexi_src_common_lib_baseservice_ts", "relation": "imports_from", "context": "import", "confidence": "EXTRACTED", "source_file": "C:\\Stayflexi\\src\\modules\\invoice\\services\\BillingService.ts", "source_location": "L2", "weight": 1.0}, {"source": "c_stayflexi_src_modules_invoice_services_billingservice_ts", "target": "lib_baseservice_baseservice", "relation": "imports", "context": "import", "confidence": "EXTRACTED", "source_file": "C:\\Stayflexi\\src\\modules\\invoice\\services\\BillingService.ts", "source_location": "L2", "weight": 1.0}, {"source": "c_stayflexi_src_modules_invoice_services_billingservice_ts", "target": "c_stayflexi_src_common_lib_prisma_ts", "relation": "imports_from", "context": "import", "confidence": "EXTRACTED", "source_file": "C:\\Stayflexi\\src\\modules\\invoice\\services\\BillingService.ts", "source_location": "L3", "weight": 1.0}, {"source": "c_stayflexi_src_modules_invoice_services_billingservice_ts", "target": "lib_prisma_prisma", "relation": "imports", "context": "import", "confidence": "EXTRACTED", "source_file": "C:\\Stayflexi\\src\\modules\\invoice\\services\\BillingService.ts", "source_location": "L3", "weight": 1.0}, {"source": "c_stayflexi_src_modules_invoice_services_billingservice_ts", "target": "c_stayflexi_src_common_errors_httperror_ts", "relation": "imports_from", "context": "import", "confidence": "EXTRACTED", "source_file": "C:\\Stayflexi\\src\\modules\\invoice\\services\\BillingService.ts", "source_location": "L4", "weight": 1.0}, {"source": "c_stayflexi_src_modules_invoice_services_billingservice_ts", "target": "errors_httperror_forbiddenerror", "relation": "imports", "context": "import", "confidence": "EXTRACTED", "source_file": "C:\\Stayflexi\\src\\modules\\invoice\\services\\BillingService.ts", "source_location": "L4", "weight": 1.0}, {"source": "c_stayflexi_src_modules_invoice_services_billingservice_ts", "target": "c_stayflexi_src_modules_invoice_repositories_prismainvoicerepository_ts", "relation": "imports_from", "context": "import", "confidence": "EXTRACTED", "source_file": "C:\\Stayflexi\\src\\modules\\invoice\\services\\BillingService.ts", "source_location": "L5", "weight": 1.0}, {"source": "c_stayflexi_src_modules_invoice_services_billingservice_ts", "target": "repositories_prismainvoicerepository_prismainvoicerepository", "relation": "imports", "context": "import", "confidence": "EXTRACTED", "source_file": "C:\\Stayflexi\\src\\modules\\invoice\\services\\BillingService.ts", "source_location": "L5", "weight": 1.0}, {"source": "c_stayflexi_src_modules_invoice_services_billingservice_ts", "target": "c_stayflexi_src_modules_invoice_dto_index_ts", "relation": "imports_from", "context": "import", "confidence": "EXTRACTED", "source_file": "C:\\Stayflexi\\src\\modules\\invoice\\services\\BillingService.ts", "source_location": "L6", "weight": 1.0}, {"source": "c_stayflexi_src_modules_invoice_services_billingservice_ts", "target": "dto_index_billingquerydtotype", "relation": "imports", "context": "import", "confidence": "EXTRACTED", "source_file": "C:\\Stayflexi\\src\\modules\\invoice\\services\\BillingService.ts", "source_location": "L6", "weight": 1.0}, {"source": "c_stayflexi_src_modules_invoice_services_billingservice_ts", "target": "services_billingservice_billingsummary", "relation": "contains", "confidence": "EXTRACTED", "source_file": "C:\\Stayflexi\\src\\modules\\invoice\\services\\BillingService.ts", "source_location": "L8", "weight": 1.0}, {"source": "c_stayflexi_src_modules_invoice_services_billingservice_ts", "target": "services_billingservice_billingservice", "relation": "contains", "confidence": "EXTRACTED", "source_file": "C:\\Stayflexi\\src\\modules\\invoice\\services\\BillingService.ts", "source_location": "L30", "weight": 1.0}, {"source": "services_billingservice_billingservice", "target": "services_billingservice_billingservice_constructor", "relation": "method", "confidence": "EXTRACTED", "source_file": "C:\\Stayflexi\\src\\modules\\invoice\\services\\BillingService.ts", "source_location": "L33", "weight": 1.0}, {"source": "services_billingservice_billingservice", "target": "services_billingservice_billingservice_getbillingsummary", "relation": "method", "confidence": "EXTRACTED", "source_file": "C:\\Stayflexi\\src\\modules\\invoice\\services\\BillingService.ts", "source_location": "L39", "weight": 1.0}], "raw_calls": [{"caller_nid": "services_billingservice_billingservice_constructor", "callee": "super", "is_member_call": false, "source_file": "C:\\Stayflexi\\src\\modules\\invoice\\services\\BillingService.ts", "source_location": "L34"}, {"caller_nid": "services_billingservice_billingservice_getbillingsummary", "callee": "execute", "is_member_call": true, "source_file": "C:\\Stayflexi\\src\\modules\\invoice\\services\\BillingService.ts", "source_location": "L43"}]}