{"nodes": [{"id": "c_stayflexi_services_ota_service_src_domain_entities_syncjob_ts", "label": "SyncJob.ts", "file_type": "code", "source_file": "C:\\Stayflexi\\services\\ota-service\\src\\domain\\entities\\SyncJob.ts", "source_location": "L1"}, {"id": "entities_syncjob_syncjobprops", "label": "SyncJobProps", "file_type": "code", "source_file": "C:\\Stayflexi\\services\\ota-service\\src\\domain\\entities\\SyncJob.ts", "source_location": "L1"}, {"id": "entities_syncjob_syncjob", "label": "SyncJob", "file_type": "code", "source_file": "C:\\Stayflexi\\services\\ota-service\\src\\domain\\entities\\SyncJob.ts", "source_location": "L20"}, {"id": "entities_syncjob_syncjob_constructor", "label": ".constructor()", "file_type": "code", "source_file": "C:\\Stayflexi\\services\\ota-service\\src\\domain\\entities\\SyncJob.ts", "source_location": "L21"}, {"id": "entities_syncjob_syncjob_id", "label": ".id()", "file_type": "code", "source_file": "C:\\Stayflexi\\services\\ota-service\\src\\domain\\entities\\SyncJob.ts", "source_location": "L23"}, {"id": "entities_syncjob_syncjob_organizationid", "label": ".organizationId()", "file_type": "code", "source_file": "C:\\Stayflexi\\services\\ota-service\\src\\domain\\entities\\SyncJob.ts", "source_location": "L24"}, {"id": "entities_syncjob_syncjob_hotelid", "label": ".hotelId()", "file_type": "code", "source_file": "C:\\Stayflexi\\services\\ota-service\\src\\domain\\entities\\SyncJob.ts", "source_location": "L25"}, {"id": "entities_syncjob_syncjob_providerid", "label": ".providerId()", "file_type": "code", "source_file": "C:\\Stayflexi\\services\\ota-service\\src\\domain\\entities\\SyncJob.ts", "source_location": "L26"}, {"id": "entities_syncjob_syncjob_synctype", "label": ".syncType()", "file_type": "code", "source_file": "C:\\Stayflexi\\services\\ota-service\\src\\domain\\entities\\SyncJob.ts", "source_location": "L27"}, {"id": "entities_syncjob_syncjob_syncstatus", "label": ".syncStatus()", "file_type": "code", "source_file": "C:\\Stayflexi\\services\\ota-service\\src\\domain\\entities\\SyncJob.ts", "source_location": "L28"}, {"id": "entities_syncjob_syncjob_idempotencykey", "label": ".idempotencyKey()", "file_type": "code", "source_file": "C:\\Stayflexi\\services\\ota-service\\src\\domain\\entities\\SyncJob.ts", "source_location": "L29"}, {"id": "entities_syncjob_syncjob_startedat", "label": ".startedAt()", "file_type": "code", "source_file": "C:\\Stayflexi\\services\\ota-service\\src\\domain\\entities\\SyncJob.ts", "source_location": "L30"}, {"id": "entities_syncjob_syncjob_completedat", "label": ".completedAt()", "file_type": "code", "source_file": "C:\\Stayflexi\\services\\ota-service\\src\\domain\\entities\\SyncJob.ts", "source_location": "L31"}, {"id": "entities_syncjob_syncjob_retrycount", "label": ".retryCount()", "file_type": "code", "source_file": "C:\\Stayflexi\\services\\ota-service\\src\\domain\\entities\\SyncJob.ts", "source_location": "L32"}, {"id": "entities_syncjob_syncjob_maxretries", "label": ".maxRetries()", "file_type": "code", "source_file": "C:\\Stayflexi\\services\\ota-service\\src\\domain\\entities\\SyncJob.ts", "source_location": "L33"}, {"id": "entities_syncjob_syncjob_errormessage", "label": ".errorMessage()", "file_type": "code", "source_file": "C:\\Stayflexi\\services\\ota-service\\src\\domain\\entities\\SyncJob.ts", "source_location": "L34"}, {"id": "entities_syncjob_syncjob_payload", "label": ".payload()", "file_type": "code", "source_file": "C:\\Stayflexi\\services\\ota-service\\src\\domain\\entities\\SyncJob.ts", "source_location": "L35"}, {"id": "entities_syncjob_syncjob_createdbyid", "label": ".createdById()", "file_type": "code", "source_file": "C:\\Stayflexi\\services\\ota-service\\src\\domain\\entities\\SyncJob.ts", "source_location": "L36"}, {"id": "entities_syncjob_syncjob_createdat", "label": ".createdAt()", "file_type": "code", "source_file": "C:\\Stayflexi\\services\\ota-service\\src\\domain\\entities\\SyncJob.ts", "source_location": "L37"}, {"id": "entities_syncjob_syncjob_updatedat", "label": ".updatedAt()", "file_type": "code", "source_file": "C:\\Stayflexi\\services\\ota-service\\src\\domain\\entities\\SyncJob.ts", "source_location": "L38"}, {"id": "entities_syncjob_syncjob_canretry", "label": ".canRetry()", "file_type": "code", "source_file": "C:\\Stayflexi\\services\\ota-service\\src\\domain\\entities\\SyncJob.ts", "source_location": "L40"}, {"id": "entities_syncjob_syncjob_ispending", "label": ".isPending()", "file_type": "code", "source_file": "C:\\Stayflexi\\services\\ota-service\\src\\domain\\entities\\SyncJob.ts", "source_location": "L44"}, {"id": "entities_syncjob_syncjob_isrunning", "label": ".isRunning()", "file_type": "code", "source_file": "C:\\Stayflexi\\services\\ota-service\\src\\domain\\entities\\SyncJob.ts", "source_location": "L48"}, {"id": "entities_syncjob_syncjob_iscompleted", "label": ".isCompleted()", "file_type": "code", "source_file": "C:\\Stayflexi\\services\\ota-service\\src\\domain\\entities\\SyncJob.ts", "source_location": "L52"}, {"id": "entities_syncjob_syncjob_tojson", "label": ".toJSON()", "file_type": "code", "source_file": "C:\\Stayflexi\\services\\ota-service\\src\\domain\\entities\\SyncJob.ts", "source_location": "L56"}], "edges": [{"source": "c_stayflexi_services_ota_service_src_domain_entities_syncjob_ts", "target": "entities_syncjob_syncjobprops", "relation": "contains", "confidence": "EXTRACTED", "source_file": "C:\\Stayflexi\\services\\ota-service\\src\\domain\\entities\\SyncJob.ts", "source_location": "L1", "weight": 1.0}, {"source": "c_stayflexi_services_ota_service_src_domain_entities_syncjob_ts", "target": "entities_syncjob_syncjob", "relation": "contains", "confidence": "EXTRACTED", "source_file": "C:\\Stayflexi\\services\\ota-service\\src\\domain\\entities\\SyncJob.ts", "source_location": "L20", "weight": 1.0}, {"source": "entities_syncjob_syncjob", "target": "entities_syncjob_syncjob_constructor", "relation": "method", "confidence": "EXTRACTED", "source_file": "C:\\Stayflexi\\services\\ota-service\\src\\domain\\entities\\SyncJob.ts", "source_location": "L21", "weight": 1.0}, {"source": "entities_syncjob_syncjob", "target": "entities_syncjob_syncjob_id", "relation": "method", "confidence": "EXTRACTED", "source_file": "C:\\Stayflexi\\services\\ota-service\\src\\domain\\entities\\SyncJob.ts", "source_location": "L23", "weight": 1.0}, {"source": "entities_syncjob_syncjob", "target": "entities_syncjob_syncjob_organizationid", "relation": "method", "confidence": "EXTRACTED", "source_file": "C:\\Stayflexi\\services\\ota-service\\src\\domain\\entities\\SyncJob.ts", "source_location": "L24", "weight": 1.0}, {"source": "entities_syncjob_syncjob", "target": "entities_syncjob_syncjob_hotelid", "relation": "method", "confidence": "EXTRACTED", "source_file": "C:\\Stayflexi\\services\\ota-service\\src\\domain\\entities\\SyncJob.ts", "source_location": "L25", "weight": 1.0}, {"source": "entities_syncjob_syncjob", "target": "entities_syncjob_syncjob_providerid", "relation": "method", "confidence": "EXTRACTED", "source_file": "C:\\Stayflexi\\services\\ota-service\\src\\domain\\entities\\SyncJob.ts", "source_location": "L26", "weight": 1.0}, {"source": "entities_syncjob_syncjob", "target": "entities_syncjob_syncjob_synctype", "relation": "method", "confidence": "EXTRACTED", "source_file": "C:\\Stayflexi\\services\\ota-service\\src\\domain\\entities\\SyncJob.ts", "source_location": "L27", "weight": 1.0}, {"source": "entities_syncjob_syncjob", "target": "entities_syncjob_syncjob_syncstatus", "relation": "method", "confidence": "EXTRACTED", "source_file": "C:\\Stayflexi\\services\\ota-service\\src\\domain\\entities\\SyncJob.ts", "source_location": "L28", "weight": 1.0}, {"source": "entities_syncjob_syncjob", "target": "entities_syncjob_syncjob_idempotencykey", "relation": "method", "confidence": "EXTRACTED", "source_file": "C:\\Stayflexi\\services\\ota-service\\src\\domain\\entities\\SyncJob.ts", "source_location": "L29", "weight": 1.0}, {"source": "entities_syncjob_syncjob", "target": "entities_syncjob_syncjob_startedat", "relation": "method", "confidence": "EXTRACTED", "source_file": "C:\\Stayflexi\\services\\ota-service\\src\\domain\\entities\\SyncJob.ts", "source_location": "L30", "weight": 1.0}, {"source": "entities_syncjob_syncjob", "target": "entities_syncjob_syncjob_completedat", "relation": "method", "confidence": "EXTRACTED", "source_file": "C:\\Stayflexi\\services\\ota-service\\src\\domain\\entities\\SyncJob.ts", "source_location": "L31", "weight": 1.0}, {"source": "entities_syncjob_syncjob", "target": "entities_syncjob_syncjob_retrycount", "relation": "method", "confidence": "EXTRACTED", "source_file": "C:\\Stayflexi\\services\\ota-service\\src\\domain\\entities\\SyncJob.ts", "source_location": "L32", "weight": 1.0}, {"source": "entities_syncjob_syncjob", "target": "entities_syncjob_syncjob_maxretries", "relation": "method", "confidence": "EXTRACTED", "source_file": "C:\\Stayflexi\\services\\ota-service\\src\\domain\\entities\\SyncJob.ts", "source_location": "L33", "weight": 1.0}, {"source": "entities_syncjob_syncjob", "target": "entities_syncjob_syncjob_errormessage", "relation": "method", "confidence": "EXTRACTED", "source_file": "C:\\Stayflexi\\services\\ota-service\\src\\domain\\entities\\SyncJob.ts", "source_location": "L34", "weight": 1.0}, {"source": "entities_syncjob_syncjob", "target": "entities_syncjob_syncjob_payload", "relation": "method", "confidence": "EXTRACTED", "source_file": "C:\\Stayflexi\\services\\ota-service\\src\\domain\\entities\\SyncJob.ts", "source_location": "L35", "weight": 1.0}, {"source": "entities_syncjob_syncjob", "target": "entities_syncjob_syncjob_createdbyid", "relation": "method", "confidence": "EXTRACTED", "source_file": "C:\\Stayflexi\\services\\ota-service\\src\\domain\\entities\\SyncJob.ts", "source_location": "L36", "weight": 1.0}, {"source": "entities_syncjob_syncjob", "target": "entities_syncjob_syncjob_createdat", "relation": "method", "confidence": "EXTRACTED", "source_file": "C:\\Stayflexi\\services\\ota-service\\src\\domain\\entities\\SyncJob.ts", "source_location": "L37", "weight": 1.0}, {"source": "entities_syncjob_syncjob", "target": "entities_syncjob_syncjob_updatedat", "relation": "method", "confidence": "EXTRACTED", "source_file": "C:\\Stayflexi\\services\\ota-service\\src\\domain\\entities\\SyncJob.ts", "source_location": "L38", "weight": 1.0}, {"source": "entities_syncjob_syncjob", "target": "entities_syncjob_syncjob_canretry", "relation": "method", "confidence": "EXTRACTED", "source_file": "C:\\Stayflexi\\services\\ota-service\\src\\domain\\entities\\SyncJob.ts", "source_location": "L40", "weight": 1.0}, {"source": "entities_syncjob_syncjob", "target": "entities_syncjob_syncjob_ispending", "relation": "method", "confidence": "EXTRACTED", "source_file": "C:\\Stayflexi\\services\\ota-service\\src\\domain\\entities\\SyncJob.ts", "source_location": "L44", "weight": 1.0}, {"source": "entities_syncjob_syncjob", "target": "entities_syncjob_syncjob_isrunning", "relation": "method", "confidence": "EXTRACTED", "source_file": "C:\\Stayflexi\\services\\ota-service\\src\\domain\\entities\\SyncJob.ts", "source_location": "L48", "weight": 1.0}, {"source": "entities_syncjob_syncjob", "target": "entities_syncjob_syncjob_iscompleted", "relation": "method", "confidence": "EXTRACTED", "source_file": "C:\\Stayflexi\\services\\ota-service\\src\\domain\\entities\\SyncJob.ts", "source_location": "L52", "weight": 1.0}, {"source": "entities_syncjob_syncjob", "target": "entities_syncjob_syncjob_tojson", "relation": "method", "confidence": "EXTRACTED", "source_file": "C:\\Stayflexi\\services\\ota-service\\src\\domain\\entities\\SyncJob.ts", "source_location": "L56", "weight": 1.0}], "raw_calls": []}