{"nodes": [{"id": "c_stayflexi_src_infrastructure_distributed_locking_types_index_ts", "label": "index.ts", "file_type": "code", "source_file": "C:\\Stayflexi\\src\\infrastructure\\distributed-locking\\types\\index.ts", "source_location": "L1"}, {"id": "types_index_idistributedlock", "label": "IDistributedLock", "file_type": "code", "source_file": "C:\\Stayflexi\\src\\infrastructure\\distributed-locking\\types\\index.ts", "source_location": "L1"}, {"id": "types_index_lockresult", "label": "LockResult", "file_type": "code", "source_file": "C:\\Stayflexi\\src\\infrastructure\\distributed-locking\\types\\index.ts", "source_location": "L9"}, {"id": "types_index_lockentry", "label": "LockEntry", "file_type": "code", "source_file": "C:\\Stayflexi\\src\\infrastructure\\distributed-locking\\types\\index.ts", "source_location": "L16"}], "edges": [{"source": "c_stayflexi_src_infrastructure_distributed_locking_types_index_ts", "target": "types_index_idistributedlock", "relation": "contains", "confidence": "EXTRACTED", "source_file": "C:\\Stayflexi\\src\\infrastructure\\distributed-locking\\types\\index.ts", "source_location": "L1", "weight": 1.0}, {"source": "c_stayflexi_src_infrastructure_distributed_locking_types_index_ts", "target": "types_index_lockresult", "relation": "contains", "confidence": "EXTRACTED", "source_file": "C:\\Stayflexi\\src\\infrastructure\\distributed-locking\\types\\index.ts", "source_location": "L9", "weight": 1.0}, {"source": "c_stayflexi_src_infrastructure_distributed_locking_types_index_ts", "target": "types_index_lockentry", "relation": "contains", "confidence": "EXTRACTED", "source_file": "C:\\Stayflexi\\src\\infrastructure\\distributed-locking\\types\\index.ts", "source_location": "L16", "weight": 1.0}], "raw_calls": []}