{"nodes": [{"id": "c_stayflexi_src_modules_pricing_types_index_ts", "label": "index.ts", "file_type": "code", "source_file": "C:\\Stayflexi\\src\\modules\\pricing\\types\\index.ts", "source_location": "L1"}, {"id": "types_index_pricingstrategytype", "label": "PricingStrategyType", "file_type": "code", "source_file": "C:\\Stayflexi\\src\\modules\\pricing\\types\\index.ts", "source_location": "L5"}, {"id": "types_index_adjustmenttypetype", "label": "AdjustmentTypeType", "file_type": "code", "source_file": "C:\\Stayflexi\\src\\modules\\pricing\\types\\index.ts", "source_location": "L14"}, {"id": "types_index_pricingrulestatustype", "label": "PricingRuleStatusType", "file_type": "code", "source_file": "C:\\Stayflexi\\src\\modules\\pricing\\types\\index.ts", "source_location": "L16"}, {"id": "types_index_pricingrule", "label": "PricingRule", "file_type": "code", "source_file": "C:\\Stayflexi\\src\\modules\\pricing\\types\\index.ts", "source_location": "L20"}, {"id": "types_index_dynamicrate", "label": "DynamicRate", "file_type": "code", "source_file": "C:\\Stayflexi\\src\\modules\\pricing\\types\\index.ts", "source_location": "L42"}, {"id": "types_index_createpricingruledata", "label": "CreatePricingRuleData", "file_type": "code", "source_file": "C:\\Stayflexi\\src\\modules\\pricing\\types\\index.ts", "source_location": "L59"}, {"id": "types_index_updatepricingruledata", "label": "UpdatePricingRuleData", "file_type": "code", "source_file": "C:\\Stayflexi\\src\\modules\\pricing\\types\\index.ts", "source_location": "L77"}, {"id": "types_index_createdynamicratedata", "label": "CreateDynamicRateData", "file_type": "code", "source_file": "C:\\Stayflexi\\src\\modules\\pricing\\types\\index.ts", "source_location": "L91"}, {"id": "types_index_updatedynamicratedata", "label": "UpdateDynamicRateData", "file_type": "code", "source_file": "C:\\Stayflexi\\src\\modules\\pricing\\types\\index.ts", "source_location": "L103"}, {"id": "types_index_pricingrulefilter", "label": "PricingRuleFilter", "file_type": "code", "source_file": "C:\\Stayflexi\\src\\modules\\pricing\\types\\index.ts", "source_location": "L112"}, {"id": "types_index_ratecalculationinput", "label": "RateCalculationInput", "file_type": "code", "source_file": "C:\\Stayflexi\\src\\modules\\pricing\\types\\index.ts", "source_location": "L124"}, {"id": "types_index_ratecalculationresult", "label": "RateCalculationResult", "file_type": "code", "source_file": "C:\\Stayflexi\\src\\modules\\pricing\\types\\index.ts", "source_location": "L132"}], "edges": [{"source": "c_stayflexi_src_modules_pricing_types_index_ts", "target": "types_index_pricingstrategytype", "relation": "contains", "confidence": "EXTRACTED", "source_file": "C:\\Stayflexi\\src\\modules\\pricing\\types\\index.ts", "source_location": "L5", "weight": 1.0}, {"source": "c_stayflexi_src_modules_pricing_types_index_ts", "target": "types_index_adjustmenttypetype", "relation": "contains", "confidence": "EXTRACTED", "source_file": "C:\\Stayflexi\\src\\modules\\pricing\\types\\index.ts", "source_location": "L14", "weight": 1.0}, {"source": "c_stayflexi_src_modules_pricing_types_index_ts", "target": "types_index_pricingrulestatustype", "relation": "contains", "confidence": "EXTRACTED", "source_file": "C:\\Stayflexi\\src\\modules\\pricing\\types\\index.ts", "source_location": "L16", "weight": 1.0}, {"source": "c_stayflexi_src_modules_pricing_types_index_ts", "target": "types_index_pricingrule", "relation": "contains", "confidence": "EXTRACTED", "source_file": "C:\\Stayflexi\\src\\modules\\pricing\\types\\index.ts", "source_location": "L20", "weight": 1.0}, {"source": "c_stayflexi_src_modules_pricing_types_index_ts", "target": "types_index_dynamicrate", "relation": "contains", "confidence": "EXTRACTED", "source_file": "C:\\Stayflexi\\src\\modules\\pricing\\types\\index.ts", "source_location": "L42", "weight": 1.0}, {"source": "c_stayflexi_src_modules_pricing_types_index_ts", "target": "types_index_createpricingruledata", "relation": "contains", "confidence": "EXTRACTED", "source_file": "C:\\Stayflexi\\src\\modules\\pricing\\types\\index.ts", "source_location": "L59", "weight": 1.0}, {"source": "c_stayflexi_src_modules_pricing_types_index_ts", "target": "types_index_updatepricingruledata", "relation": "contains", "confidence": "EXTRACTED", "source_file": "C:\\Stayflexi\\src\\modules\\pricing\\types\\index.ts", "source_location": "L77", "weight": 1.0}, {"source": "c_stayflexi_src_modules_pricing_types_index_ts", "target": "types_index_createdynamicratedata", "relation": "contains", "confidence": "EXTRACTED", "source_file": "C:\\Stayflexi\\src\\modules\\pricing\\types\\index.ts", "source_location": "L91", "weight": 1.0}, {"source": "c_stayflexi_src_modules_pricing_types_index_ts", "target": "types_index_updatedynamicratedata", "relation": "contains", "confidence": "EXTRACTED", "source_file": "C:\\Stayflexi\\src\\modules\\pricing\\types\\index.ts", "source_location": "L103", "weight": 1.0}, {"source": "c_stayflexi_src_modules_pricing_types_index_ts", "target": "types_index_pricingrulefilter", "relation": "contains", "confidence": "EXTRACTED", "source_file": "C:\\Stayflexi\\src\\modules\\pricing\\types\\index.ts", "source_location": "L112", "weight": 1.0}, {"source": "c_stayflexi_src_modules_pricing_types_index_ts", "target": "types_index_ratecalculationinput", "relation": "contains", "confidence": "EXTRACTED", "source_file": "C:\\Stayflexi\\src\\modules\\pricing\\types\\index.ts", "source_location": "L124", "weight": 1.0}, {"source": "c_stayflexi_src_modules_pricing_types_index_ts", "target": "types_index_ratecalculationresult", "relation": "contains", "confidence": "EXTRACTED", "source_file": "C:\\Stayflexi\\src\\modules\\pricing\\types\\index.ts", "source_location": "L132", "weight": 1.0}], "raw_calls": []}