{"nodes": [{"id": "c_stayflexi_src_modules_synchronization_services_syncjobservice_ts", "label": "SyncJobService.ts", "file_type": "code", "source_file": "C:\\Stayflexi\\src\\modules\\synchronization\\services\\SyncJobService.ts", "source_location": "L1"}, {"id": "services_syncjobservice_syncjobservice", "label": "SyncJobService", "file_type": "code", "source_file": "C:\\Stayflexi\\src\\modules\\synchronization\\services\\SyncJobService.ts", "source_location": "L15"}, {"id": "services_syncjobservice_syncjobservice_constructor", "label": ".constructor()", "file_type": "code", "source_file": "C:\\Stayflexi\\src\\modules\\synchronization\\services\\SyncJobService.ts", "source_location": "L18"}, {"id": "services_syncjobservice_syncjobservice_validatejoborgaccess", "label": ".validateJobOrgAccess()", "file_type": "code", "source_file": "C:\\Stayflexi\\src\\modules\\synchronization\\services\\SyncJobService.ts", "source_location": "L27"}, {"id": "services_syncjobservice_syncjobservice_createsyncjob", "label": ".createSyncJob()", "file_type": "code", "source_file": "C:\\Stayflexi\\src\\modules\\synchronization\\services\\SyncJobService.ts", "source_location": "L36"}, {"id": "services_syncjobservice_syncjobservice_executesyncjob", "label": ".executeSyncJob()", "file_type": "code", "source_file": "C:\\Stayflexi\\src\\modules\\synchronization\\services\\SyncJobService.ts", "source_location": "L124"}, {"id": "services_syncjobservice_syncjobservice_retrysyncjob", "label": ".retrySyncJob()", "file_type": "code", "source_file": "C:\\Stayflexi\\src\\modules\\synchronization\\services\\SyncJobService.ts", "source_location": "L230"}, {"id": "services_syncjobservice_syncjobservice_cancelsyncjob", "label": ".cancelSyncJob()", "file_type": "code", "source_file": "C:\\Stayflexi\\src\\modules\\synchronization\\services\\SyncJobService.ts", "source_location": "L278"}, {"id": "services_syncjobservice_syncjobservice_listsyncjobs", "label": ".listSyncJobs()", "file_type": "code", "source_file": "C:\\Stayflexi\\src\\modules\\synchronization\\services\\SyncJobService.ts", "source_location": "L294"}, {"id": "services_syncjobservice_syncjobservice_getsyncjob", "label": ".getSyncJob()", "file_type": "code", "source_file": "C:\\Stayflexi\\src\\modules\\synchronization\\services\\SyncJobService.ts", "source_location": "L324"}, {"id": "services_syncjobservice_syncjobservice_getsyncevents", "label": ".getSyncEvents()", "file_type": "code", "source_file": "C:\\Stayflexi\\src\\modules\\synchronization\\services\\SyncJobService.ts", "source_location": "L332"}], "edges": [{"source": "c_stayflexi_src_modules_synchronization_services_syncjobservice_ts", "target": "c_stayflexi_src_common_lib_baseservice_ts", "relation": "imports_from", "context": "import", "confidence": "EXTRACTED", "source_file": "C:\\Stayflexi\\src\\modules\\synchronization\\services\\SyncJobService.ts", "source_location": "L2", "weight": 1.0}, {"source": "c_stayflexi_src_modules_synchronization_services_syncjobservice_ts", "target": "lib_baseservice_baseservice", "relation": "imports", "context": "import", "confidence": "EXTRACTED", "source_file": "C:\\Stayflexi\\src\\modules\\synchronization\\services\\SyncJobService.ts", "source_location": "L2", "weight": 1.0}, {"source": "c_stayflexi_src_modules_synchronization_services_syncjobservice_ts", "target": "c_stayflexi_src_common_lib_prisma_ts", "relation": "imports_from", "context": "import", "confidence": "EXTRACTED", "source_file": "C:\\Stayflexi\\src\\modules\\synchronization\\services\\SyncJobService.ts", "source_location": "L3", "weight": 1.0}, {"source": "c_stayflexi_src_modules_synchronization_services_syncjobservice_ts", "target": "lib_prisma_prisma", "relation": "imports", "context": "import", "confidence": "EXTRACTED", "source_file": "C:\\Stayflexi\\src\\modules\\synchronization\\services\\SyncJobService.ts", "source_location": "L3", "weight": 1.0}, {"source": "c_stayflexi_src_modules_synchronization_services_syncjobservice_ts", "target": "c_stayflexi_src_common_errors_httperror_ts", "relation": "imports_from", "context": "import", "confidence": "EXTRACTED", "source_file": "C:\\Stayflexi\\src\\modules\\synchronization\\services\\SyncJobService.ts", "source_location": "L4", "weight": 1.0}, {"source": "c_stayflexi_src_modules_synchronization_services_syncjobservice_ts", "target": "errors_httperror_notfounderror", "relation": "imports", "context": "import", "confidence": "EXTRACTED", "source_file": "C:\\Stayflexi\\src\\modules\\synchronization\\services\\SyncJobService.ts", "source_location": "L4", "weight": 1.0}, {"source": "c_stayflexi_src_modules_synchronization_services_syncjobservice_ts", "target": "errors_httperror_conflicterror", "relation": "imports", "context": "import", "confidence": "EXTRACTED", "source_file": "C:\\Stayflexi\\src\\modules\\synchronization\\services\\SyncJobService.ts", "source_location": "L4", "weight": 1.0}, {"source": "c_stayflexi_src_modules_synchronization_services_syncjobservice_ts", "target": "errors_httperror_forbiddenerror", "relation": "imports", "context": "import", "confidence": "EXTRACTED", "source_file": "C:\\Stayflexi\\src\\modules\\synchronization\\services\\SyncJobService.ts", "source_location": "L4", "weight": 1.0}, {"source": "c_stayflexi_src_modules_synchronization_services_syncjobservice_ts", "target": "errors_httperror_badrequesterror", "relation": "imports", "context": "import", "confidence": "EXTRACTED", "source_file": "C:\\Stayflexi\\src\\modules\\synchronization\\services\\SyncJobService.ts", "source_location": "L4", "weight": 1.0}, {"source": "c_stayflexi_src_modules_synchronization_services_syncjobservice_ts", "target": "c_stayflexi_src_common_types_index_ts", "relation": "imports_from", "context": "import", "confidence": "EXTRACTED", "source_file": "C:\\Stayflexi\\src\\modules\\synchronization\\services\\SyncJobService.ts", "source_location": "L5", "weight": 1.0}, {"source": "c_stayflexi_src_modules_synchronization_services_syncjobservice_ts", "target": "types_index_paginatedresult", "relation": "imports", "context": "import", "confidence": "EXTRACTED", "source_file": "C:\\Stayflexi\\src\\modules\\synchronization\\services\\SyncJobService.ts", "source_location": "L5", "weight": 1.0}, {"source": "c_stayflexi_src_modules_synchronization_services_syncjobservice_ts", "target": "c_stayflexi_src_modules_synchronization_repositories_prismasyncjobrepository_ts", "relation": "imports_from", "context": "import", "confidence": "EXTRACTED", "source_file": "C:\\Stayflexi\\src\\modules\\synchronization\\services\\SyncJobService.ts", "source_location": "L6", "weight": 1.0}, {"source": "c_stayflexi_src_modules_synchronization_services_syncjobservice_ts", "target": "repositories_prismasyncjobrepository_prismasyncjobrepository", "relation": "imports", "context": "import", "confidence": "EXTRACTED", "source_file": "C:\\Stayflexi\\src\\modules\\synchronization\\services\\SyncJobService.ts", "source_location": "L6", "weight": 1.0}, {"source": "c_stayflexi_src_modules_synchronization_services_syncjobservice_ts", "target": "c_stayflexi_src_modules_synchronization_repositories_prismasynceventrepository_ts", "relation": "imports_from", "context": "import", "confidence": "EXTRACTED", "source_file": "C:\\Stayflexi\\src\\modules\\synchronization\\services\\SyncJobService.ts", "source_location": "L7", "weight": 1.0}, {"source": "c_stayflexi_src_modules_synchronization_services_syncjobservice_ts", "target": "repositories_prismasynceventrepository_prismasynceventrepository", "relation": "imports", "context": "import", "confidence": "EXTRACTED", "source_file": "C:\\Stayflexi\\src\\modules\\synchronization\\services\\SyncJobService.ts", "source_location": "L7", "weight": 1.0}, {"source": "c_stayflexi_src_modules_synchronization_services_syncjobservice_ts", "target": "c_stayflexi_src_modules_synchronization_types_index_ts", "relation": "imports_from", "context": "import", "confidence": "EXTRACTED", "source_file": "C:\\Stayflexi\\src\\modules\\synchronization\\services\\SyncJobService.ts", "source_location": "L8", "weight": 1.0}, {"source": "c_stayflexi_src_modules_synchronization_services_syncjobservice_ts", "target": "types_index_syncjob", "relation": "imports", "context": "import", "confidence": "EXTRACTED", "source_file": "C:\\Stayflexi\\src\\modules\\synchronization\\services\\SyncJobService.ts", "source_location": "L8", "weight": 1.0}, {"source": "c_stayflexi_src_modules_synchronization_services_syncjobservice_ts", "target": "types_index_syncevent", "relation": "imports", "context": "import", "confidence": "EXTRACTED", "source_file": "C:\\Stayflexi\\src\\modules\\synchronization\\services\\SyncJobService.ts", "source_location": "L8", "weight": 1.0}, {"source": "c_stayflexi_src_modules_synchronization_services_syncjobservice_ts", "target": "types_index_syncjobfilter", "relation": "imports", "context": "import", "confidence": "EXTRACTED", "source_file": "C:\\Stayflexi\\src\\modules\\synchronization\\services\\SyncJobService.ts", "source_location": "L8", "weight": 1.0}, {"source": "c_stayflexi_src_modules_synchronization_services_syncjobservice_ts", "target": "c_stayflexi_src_modules_synchronization_dto_index_ts", "relation": "imports_from", "context": "import", "confidence": "EXTRACTED", "source_file": "C:\\Stayflexi\\src\\modules\\synchronization\\services\\SyncJobService.ts", "source_location": "L9", "weight": 1.0}, {"source": "c_stayflexi_src_modules_synchronization_services_syncjobservice_ts", "target": "dto_index_createsyncjobdtotype", "relation": "imports", "context": "import", "confidence": "EXTRACTED", "source_file": "C:\\Stayflexi\\src\\modules\\synchronization\\services\\SyncJobService.ts", "source_location": "L9", "weight": 1.0}, {"source": "c_stayflexi_src_modules_synchronization_services_syncjobservice_ts", "target": "dto_index_syncjobfilterdtotype", "relation": "imports", "context": "import", "confidence": "EXTRACTED", "source_file": "C:\\Stayflexi\\src\\modules\\synchronization\\services\\SyncJobService.ts", "source_location": "L9", "weight": 1.0}, {"source": "c_stayflexi_src_modules_synchronization_services_syncjobservice_ts", "target": "c_stayflexi_src_modules_synchronization_constants_index_ts", "relation": "imports_from", "context": "import", "confidence": "EXTRACTED", "source_file": "C:\\Stayflexi\\src\\modules\\synchronization\\services\\SyncJobService.ts", "source_location": "L10", "weight": 1.0}, {"source": "c_stayflexi_src_modules_synchronization_services_syncjobservice_ts", "target": "constants_index_sync_errors", "relation": "imports", "context": "import", "confidence": "EXTRACTED", "source_file": "C:\\Stayflexi\\src\\modules\\synchronization\\services\\SyncJobService.ts", "source_location": "L10", "weight": 1.0}, {"source": "c_stayflexi_src_modules_synchronization_services_syncjobservice_ts", "target": "constants_index_retry_backoff_base_ms", "relation": "imports", "context": "import", "confidence": "EXTRACTED", "source_file": "C:\\Stayflexi\\src\\modules\\synchronization\\services\\SyncJobService.ts", "source_location": "L10", "weight": 1.0}, {"source": "c_stayflexi_src_modules_synchronization_services_syncjobservice_ts", "target": "c_stayflexi_src_modules_synchronization_strategies_syncstrategyregistry_ts", "relation": "imports_from", "context": "import", "confidence": "EXTRACTED", "source_file": "C:\\Stayflexi\\src\\modules\\synchronization\\services\\SyncJobService.ts", "source_location": "L11", "weight": 1.0}, {"source": "c_stayflexi_src_modules_synchronization_services_syncjobservice_ts", "target": "strategies_syncstrategyregistry_syncstrategyregistry", "relation": "imports", "context": "import", "confidence": "EXTRACTED", "source_file": "C:\\Stayflexi\\src\\modules\\synchronization\\services\\SyncJobService.ts", "source_location": "L11", "weight": 1.0}, {"source": "c_stayflexi_src_modules_synchronization_services_syncjobservice_ts", "target": "c_stayflexi_src_modules_synchronization_queues_index_ts", "relation": "imports_from", "context": "import", "confidence": "EXTRACTED", "source_file": "C:\\Stayflexi\\src\\modules\\synchronization\\services\\SyncJobService.ts", "source_location": "L12", "weight": 1.0}, {"source": "c_stayflexi_src_modules_synchronization_services_syncjobservice_ts", "target": "queues_index_syncqueue", "relation": "imports", "context": "import", "confidence": "EXTRACTED", "source_file": "C:\\Stayflexi\\src\\modules\\synchronization\\services\\SyncJobService.ts", "source_location": "L12", "weight": 1.0}, {"source": "c_stayflexi_src_modules_synchronization_services_syncjobservice_ts", "target": "queues_index_retryqueue", "relation": "imports", "context": "import", "confidence": "EXTRACTED", "source_file": "C:\\Stayflexi\\src\\modules\\synchronization\\services\\SyncJobService.ts", "source_location": "L12", "weight": 1.0}, {"source": "c_stayflexi_src_modules_synchronization_services_syncjobservice_ts", "target": "queues_index_deadletterqueue", "relation": "imports", "context": "import", "confidence": "EXTRACTED", "source_file": "C:\\Stayflexi\\src\\modules\\synchronization\\services\\SyncJobService.ts", "source_location": "L12", "weight": 1.0}, {"source": "c_stayflexi_src_modules_synchronization_services_syncjobservice_ts", "target": "c_stayflexi_src_modules_synchronization_queues_retryqueue_ts", "relation": "imports_from", "context": "import", "confidence": "EXTRACTED", "source_file": "C:\\Stayflexi\\src\\modules\\synchronization\\services\\SyncJobService.ts", "source_location": "L13", "weight": 1.0}, {"source": "c_stayflexi_src_modules_synchronization_services_syncjobservice_ts", "target": "queues_retryqueue_computeretrydelay", "relation": "imports", "context": "import", "confidence": "EXTRACTED", "source_file": "C:\\Stayflexi\\src\\modules\\synchronization\\services\\SyncJobService.ts", "source_location": "L13", "weight": 1.0}, {"source": "c_stayflexi_src_modules_synchronization_services_syncjobservice_ts", "target": "services_syncjobservice_syncjobservice", "relation": "contains", "confidence": "EXTRACTED", "source_file": "C:\\Stayflexi\\src\\modules\\synchronization\\services\\SyncJobService.ts", "source_location": "L15", "weight": 1.0}, {"source": "services_syncjobservice_syncjobservice", "target": "services_syncjobservice_syncjobservice_constructor", "relation": "method", "confidence": "EXTRACTED", "source_file": "C:\\Stayflexi\\src\\modules\\synchronization\\services\\SyncJobService.ts", "source_location": "L18", "weight": 1.0}, {"source": "services_syncjobservice_syncjobservice", "target": "services_syncjobservice_syncjobservice_validatejoborgaccess", "relation": "method", "confidence": "EXTRACTED", "source_file": "C:\\Stayflexi\\src\\modules\\synchronization\\services\\SyncJobService.ts", "source_location": "L27", "weight": 1.0}, {"source": "services_syncjobservice_syncjobservice", "target": "services_syncjobservice_syncjobservice_createsyncjob", "relation": "method", "confidence": "EXTRACTED", "source_file": "C:\\Stayflexi\\src\\modules\\synchronization\\services\\SyncJobService.ts", "source_location": "L36", "weight": 1.0}, {"source": "services_syncjobservice_syncjobservice", "target": "services_syncjobservice_syncjobservice_executesyncjob", "relation": "method", "confidence": "EXTRACTED", "source_file": "C:\\Stayflexi\\src\\modules\\synchronization\\services\\SyncJobService.ts", "source_location": "L124", "weight": 1.0}, {"source": "services_syncjobservice_syncjobservice", "target": "services_syncjobservice_syncjobservice_retrysyncjob", "relation": "method", "confidence": "EXTRACTED", "source_file": "C:\\Stayflexi\\src\\modules\\synchronization\\services\\SyncJobService.ts", "source_location": "L230", "weight": 1.0}, {"source": "services_syncjobservice_syncjobservice", "target": "services_syncjobservice_syncjobservice_cancelsyncjob", "relation": "method", "confidence": "EXTRACTED", "source_file": "C:\\Stayflexi\\src\\modules\\synchronization\\services\\SyncJobService.ts", "source_location": "L278", "weight": 1.0}, {"source": "services_syncjobservice_syncjobservice", "target": "services_syncjobservice_syncjobservice_listsyncjobs", "relation": "method", "confidence": "EXTRACTED", "source_file": "C:\\Stayflexi\\src\\modules\\synchronization\\services\\SyncJobService.ts", "source_location": "L294", "weight": 1.0}, {"source": "services_syncjobservice_syncjobservice", "target": "services_syncjobservice_syncjobservice_getsyncjob", "relation": "method", "confidence": "EXTRACTED", "source_file": "C:\\Stayflexi\\src\\modules\\synchronization\\services\\SyncJobService.ts", "source_location": "L324", "weight": 1.0}, {"source": "services_syncjobservice_syncjobservice", "target": "services_syncjobservice_syncjobservice_getsyncevents", "relation": "method", "confidence": "EXTRACTED", "source_file": "C:\\Stayflexi\\src\\modules\\synchronization\\services\\SyncJobService.ts", "source_location": "L332", "weight": 1.0}], "raw_calls": [{"caller_nid": "services_syncjobservice_syncjobservice_constructor", "callee": "super", "is_member_call": false, "source_file": "C:\\Stayflexi\\src\\modules\\synchronization\\services\\SyncJobService.ts", "source_location": "L22"}, {"caller_nid": "services_syncjobservice_syncjobservice_validatejoborgaccess", "callee": "findById", "is_member_call": true, "source_file": "C:\\Stayflexi\\src\\modules\\synchronization\\services\\SyncJobService.ts", "source_location": "L28"}, {"caller_nid": "services_syncjobservice_syncjobservice_createsyncjob", "callee": "execute", "is_member_call": true, "source_file": "C:\\Stayflexi\\src\\modules\\synchronization\\services\\SyncJobService.ts", "source_location": "L41"}, {"caller_nid": "services_syncjobservice_syncjobservice_executesyncjob", "callee": "execute", "is_member_call": true, "source_file": "C:\\Stayflexi\\src\\modules\\synchronization\\services\\SyncJobService.ts", "source_location": "L125"}, {"caller_nid": "services_syncjobservice_syncjobservice_retrysyncjob", "callee": "execute", "is_member_call": true, "source_file": "C:\\Stayflexi\\src\\modules\\synchronization\\services\\SyncJobService.ts", "source_location": "L231"}, {"caller_nid": "services_syncjobservice_syncjobservice_cancelsyncjob", "callee": "execute", "is_member_call": true, "source_file": "C:\\Stayflexi\\src\\modules\\synchronization\\services\\SyncJobService.ts", "source_location": "L279"}, {"caller_nid": "services_syncjobservice_syncjobservice_listsyncjobs", "callee": "execute", "is_member_call": true, "source_file": "C:\\Stayflexi\\src\\modules\\synchronization\\services\\SyncJobService.ts", "source_location": "L298"}, {"caller_nid": "services_syncjobservice_syncjobservice_getsyncjob", "callee": "execute", "is_member_call": true, "source_file": "C:\\Stayflexi\\src\\modules\\synchronization\\services\\SyncJobService.ts", "source_location": "L325"}, {"caller_nid": "services_syncjobservice_syncjobservice_getsyncevents", "callee": "execute", "is_member_call": true, "source_file": "C:\\Stayflexi\\src\\modules\\synchronization\\services\\SyncJobService.ts", "source_location": "L333"}]}